{
    "projects": [
        {
            "id": "merck-rnd",
            "title": "MERCK",
            "slug": "merck-rnd",
            "category": "healthcare",
            "tags": [
                "Healthcare",
                "AI"
            ],
            "thumbnail": "/images/projects/merck-thumb.jpg",
            "heroImage": "/images/projects/merck-hero.jpg",
            "description": "Revolutionized R&D productivity with AI-powered data analysis platform.",
            "client": "Merck Pharmaceuticals",
            "year": "2024",
            "services": [
                "AI Development",
                "Data Analytics",
                "Cloud Architecture"
            ],
            "stats": {
                "value": "99%",
                "label": "Faster R&D"
            },
            "featured": true
        },
        {
            "id": "realestate-ai",
            "title": "PROPTECH AI",
            "slug": "realestate-ai",
            "category": "proptech",
            "tags": [
                "PropTech",
                "AI"
            ],
            "thumbnail": "/images/projects/proptech-thumb.jpg",
            "heroImage": "/images/projects/proptech-hero.jpg",
            "description": "Hyper-personalized property recommendations using machine learning.",
            "client": "Real Estate Startup",
            "year": "2024",
            "services": [
                "Machine Learning",
                "Web Development",
                "UX Design"
            ],
            "stats": {
                "value": "60%",
                "label": "Engagement Boost"
            },
            "featured": true
        },
        {
            "id": "mobile-redesign",
            "title": "MOBILE APP",
            "slug": "mobile-redesign",
            "category": "mobile",
            "tags": [
                "Mobile",
                "React Native"
            ],
            "thumbnail": "/images/projects/mobile-thumb.jpg",
            "heroImage": "/images/projects/mobile-hero.jpg",
            "description": "Complete redesign and development of e-commerce mobile application.",
            "client": "E-Commerce Brand",
            "year": "2024",
            "services": [
                "Mobile Development",
                "UI/UX Design",
                "API Integration"
            ],
            "stats": {
                "value": "2x",
                "label": "Faster Delivery"
            },
            "featured": true
        },
        {
            "id": "fintech-platform",
            "title": "FINTECH",
            "slug": "fintech-platform",
            "category": "finance",
            "tags": [
                "Finance",
                "Web App"
            ],
            "thumbnail": "/images/projects/fintech-thumb.jpg",
            "heroImage": "/images/projects/fintech-hero.jpg",
            "description": "Secure payment gateway and risk management dashboard.",
            "client": "Financial Services",
            "year": "2023",
            "services": [
                "Web Development",
                "Payment Integration",
                "Security Audit"
            ],
            "stats": {
                "value": "5x",
                "label": "ROI Increase"
            },
            "featured": false
        },
        {
            "id": "ecommerce-marketplace",
            "title": "MARKETPLACE",
            "slug": "ecommerce-marketplace",
            "category": "commerce",
            "tags": [
                "E-Commerce",
                "Full Stack"
            ],
            "thumbnail": "/images/projects/ecommerce-thumb.jpg",
            "heroImage": "/images/projects/ecommerce-hero.jpg",
            "description": "Multi-vendor marketplace with advanced inventory management.",
            "client": "Retail Corporation",
            "year": "2023",
            "services": [
                "Full Stack Development",
                "Database Design",
                "DevOps"
            ],
            "stats": {
                "value": "77%",
                "label": "Faster Delivery"
            },
            "featured": false
        },
        {
            "id": "edtech-platform",
            "title": "EDTECH LMS",
            "slug": "edtech-platform",
            "category": "education",
            "tags": [
                "Education",
                "SaaS"
            ],
            "thumbnail": "/images/projects/edtech-thumb.jpg",
            "heroImage": "/images/projects/edtech-hero.jpg",
            "description": "Learning management system with virtual classrooms and assessments.",
            "client": "Education Startup",
            "year": "2023",
            "services": [
                "SaaS Development",
                "Video Integration",
                "Analytics"
            ],
            "stats": {
                "value": "2x",
                "label": "User Engagement"
            },
            "featured": false
        },
        {
            "id": "healthcare-app",
            "title": "TELEHEALTH",
            "slug": "healthcare-app",
            "category": "healthcare",
            "tags": [
                "Healthcare",
                "Mobile"
            ],
            "thumbnail": "/images/projects/telehealth-thumb.jpg",
            "heroImage": "/images/projects/telehealth-hero.jpg",
            "description": "Telemedicine app connecting patients with healthcare providers.",
            "client": "Healthcare Provider",
            "year": "2024",
            "services": [
                "Mobile Development",
                "HIPAA Compliance",
                "Video Calling"
            ],
            "stats": {
                "value": "50K+",
                "label": "Active Users"
            },
            "featured": false
        },
        {
            "id": "ai-chatbot",
            "title": "AI ASSISTANT",
            "slug": "ai-chatbot",
            "category": "ai",
            "tags": [
                "AI",
                "NLP"
            ],
            "thumbnail": "/images/projects/ai-thumb.jpg",
            "heroImage": "/images/projects/ai-hero.jpg",
            "description": "Intelligent customer support chatbot with natural language processing.",
            "client": "Tech Enterprise",
            "year": "2024",
            "services": [
                "NLP Development",
                "API Integration",
                "Cloud Deployment"
            ],
            "stats": {
                "value": "80%",
                "label": "Query Resolution"
            },
            "featured": false
        }
    ],
    "categories": [
        {
            "id": "all",
            "label": "All Works"
        },
        {
            "id": "healthcare",
            "label": "Healthcare"
        },
        {
            "id": "finance",
            "label": "Finance"
        },
        {
            "id": "commerce",
            "label": "E-Commerce"
        },
        {
            "id": "education",
            "label": "Education"
        },
        {
            "id": "proptech",
            "label": "PropTech"
        },
        {
            "id": "ai",
            "label": "AI/ML"
        },
        {
            "id": "mobile",
            "label": "Mobile"
        }
    ],
    "tags": [
        "Healthcare",
        "AI",
        "PropTech",
        "Mobile",
        "React Native",
        "Finance",
        "Web App",
        "E-Commerce",
        "Full Stack",
        "Education",
        "SaaS",
        "NLP"
    ]
}